[
    {
      "_id": "61e5d509c2aebc0b97d33e02",
      "city": "61e5d4d1c2aebc0b97d33e01",
      "date": "2024-02-13",
      "minTemperature": 20,
      "maxTemperature": 35,
      "precipitationProbability": 30,
      "windSpeed": 10,
      "windDirection": "NW",
      "humidity": 60
    },
    {
      "_id": "61e5d509c2aebc0b97d33e03",
      "city": "61e5d4d1c2aebc0b97d33e01",
      "date": "2024-02-14",
      "minTemperature": 22,
      "maxTemperature": 36,
      "precipitationProbability": 20,
      "windSpeed": 12,
      "windDirection": "W",
      "humidity": 55
    },
    {
      "_id": "61e5d509c2aebc0b97d33e04",
      "city": "61e5d4d1c2aebc0b97d33e01",
      "date": "2024-02-15",
      "minTemperature": 25,
      "maxTemperature": 38,
      "precipitationProbability": 40,
      "windSpeed": 15,
      "windDirection": "SW",
      "humidity": 70
    },
    {
      "_id": "61e5d509c2aebc0b97d33e06",
      "city": "61e5d4d1c2aebc0b97d33e05",
      "date": "2024-02-13",
      "minTemperature": 5,
      "maxTemperature": 10,
      "precipitationProbability": 60,
      "windSpeed": 20,
      "windDirection": "N",
      "humidity": 75
    },
    {
      "_id": "61e5d509c2aebc0b97d33e07",
      "city": "61e5d4d1c2aebc0b97d33e05",
      "date": "2024-02-14",
      "minTemperature": 6,
      "maxTemperature": 11,
      "precipitationProbability": 70,
      "windSpeed": 18,
      "windDirection": "NE",
      "humidity": 80
    },
    {
      "_id": "61e5d509c2aebc0b97d33e08",
      "city": "61e5d4d1c2aebc0b97d33e05",
      "date": "2024-02-15",
      "minTemperature": 8,
      "maxTemperature": 13,
      "precipitationProbability": 50,
      "windSpeed": 15,
      "windDirection": "E",
      "humidity": 70
    }
  ]